virgo/.gitignore
virgo/__init__.py
virgo/graph.py
virgo/internal.py
virgo/load.py
virgo/parse.py
virgo/preprocess.py
pyvirgo36-0.2.1.dist-info/LICENSE
pyvirgo36-0.2.1.dist-info/WHEEL
pyvirgo36-0.2.1.dist-info/METADATA
pyvirgo36-0.2.1.dist-info/RECORD
